schiavinato_sharing/__init__.py
schiavinato_sharing/checksums.py
schiavinato_sharing/field.py
schiavinato_sharing/lagrange.py
schiavinato_sharing/polynomial.py
schiavinato_sharing/recover.py
schiavinato_sharing/security.py
schiavinato_sharing/seed.py
schiavinato_sharing/split.py
schiavinato_sharing/types.py
schiavinato_sharing-0.4.0.dist-info/METADATA
schiavinato_sharing-0.4.0.dist-info/WHEEL
schiavinato_sharing-0.4.0.dist-info/top_level.txt
schiavinato_sharing-0.4.0.dist-info/RECORD
