Metadata-Version: 2.4
Name: schiavinato-sharing
Version: 0.4.0
Summary: Human-executable secret sharing for BIP39 mnemonics using GF(2053)
Author-email: GRIFORTIS <info@grifortis.com>
Maintainer-email: Renato Schiavinato Lopez <renato@grifortis.com>
License: MIT
Project-URL: Homepage, https://github.com/GRIFORTIS/schiavinato-sharing-py
Project-URL: Documentation, https://github.com/GRIFORTIS/schiavinato-sharing-spec
Project-URL: Repository, https://github.com/GRIFORTIS/schiavinato-sharing-py
Project-URL: Issues, https://github.com/GRIFORTIS/schiavinato-sharing-py/issues
Project-URL: Changelog, https://github.com/GRIFORTIS/schiavinato-sharing-py/blob/main/CHANGELOG.md
Keywords: bip39,shamir,secret-sharing,mnemonic,cryptocurrency,bitcoin,inheritance,backup,schiavinato,gf2053
Classifier: Development Status :: 2 - Pre-Alpha
Classifier: Intended Audience :: Developers
Classifier: License :: OSI Approved :: MIT License
Classifier: Programming Language :: Python :: 3
Classifier: Programming Language :: Python :: 3.10
Classifier: Programming Language :: Python :: 3.11
Classifier: Programming Language :: Python :: 3.12
Classifier: Topic :: Security :: Cryptography
Classifier: Topic :: Software Development :: Libraries :: Python Modules
Requires-Python: >=3.10
Requires-Dist: mnemonic>=0.20
Provides-Extra: dev
Requires-Dist: pytest==9.0.2; extra == "dev"
Requires-Dist: pytest-cov==7.0.0; extra == "dev"
Requires-Dist: mypy==1.19.1; extra == "dev"
Requires-Dist: black==26.1.0; extra == "dev"
Requires-Dist: ruff==0.14.14; extra == "dev"
Requires-Dist: isort==7.0.0; extra == "dev"
